paymentcorner/__init__.py
paymentcorner/auth.py
paymentcorner/client.py
paymentcorner/config.py
paymentcorner/error.py
paymentcorner/http.py
payment_corner-0.0.2.dist-info/LICENSE.md
payment_corner-0.0.2.dist-info/METADATA
payment_corner-0.0.2.dist-info/WHEEL
payment_corner-0.0.2.dist-info/top_level.txt
payment_corner-0.0.2.dist-info/RECORD
